jsonschema_mdit/__init__.py
jsonschema_mdit/main.py
jsonschema_mdit/meta.py
jsonschema_mdit/protocol.py
jsonschema_mdit/schema.py
jsonschema_mdit/generator/__init__.py
jsonschema_mdit/generator/default.py
JSONSchema_MDit-0.0.0.dev6.dist-info/METADATA
JSONSchema_MDit-0.0.0.dev6.dist-info/WHEEL
JSONSchema_MDit-0.0.0.dev6.dist-info/top_level.txt
JSONSchema_MDit-0.0.0.dev6.dist-info/RECORD
