Metadata-Version: 2.1
Name: JSONSchema-MDit
Version: 0.0.0.dev6
Requires-Python: >=3.10
Requires-Dist: MDit==0.0.0.dev56
Requires-Dist: PySerials==0.0.0.dev59
Requires-Dist: PyLinks==0.0.0.dev69
